README.md
setup.py
WeatherLookup/__init__.py
WeatherLookup.egg-info/PKG-INFO
WeatherLookup.egg-info/SOURCES.txt
WeatherLookup.egg-info/dependency_links.txt
WeatherLookup.egg-info/requires.txt
WeatherLookup.egg-info/top_level.txt