Metadata-Version: 2.1
Name: WeatherLookup
Version: 1.0.1
Summary: Look up live weather data from across the world
Home-page: https://github.com/mustafaisnotsmart/WeatherLibrary
Author: Mustafa A
License: MIT
Platform: UNKNOWN
